{
  "timestamp": "2026-01-02T15:46:12.515313",
  "total": {
    "value": 47
  },
  "drivers": {
    "fear_greed": {
      "label": "Fear & Greed",
      "value": 28,
      "delta": 0
    },
    "news": {
      "label": "News Sentiment",
      "value": 47,
      "delta": -4
    },
    "social": {
      "label": "Social Buzz",
      "value": 58,
      "delta": 6
    },
    "price_action": {
      "label": "Price Action",
      "value": 56,
      "delta": 3
    },
    "on_chain": {
      "label": "On-chain Activity",
      "value": 40,
      "delta": -1
    },
    "liquidity": {
      "label": "Liquidity",
      "value": 54,
      "delta": 1
    }
  },
  "value": 47,
  "fear_greed": 28,
  "news_sentiment": 47,
  "price_sentiment": 56,
  "price_change_24h": 1.99174,
  "liquidity_sentiment": 54
}