{
  "timestamp": "2025-12-23T03:54:32.609377",
  "total": {
    "value": 44
  },
  "drivers": {
    "fear_greed": {
      "label": "Fear & Greed",
      "value": 24,
      "delta": -1
    },
    "news": {
      "label": "News Sentiment",
      "value": 49,
      "delta": -7
    },
    "social": {
      "label": "Social Buzz",
      "value": 49,
      "delta": -4
    },
    "price_action": {
      "label": "Price Action",
      "value": 48,
      "delta": -3
    },
    "on_chain": {
      "label": "On-chain Activity",
      "value": 47,
      "delta": -4
    },
    "liquidity": {
      "label": "Liquidity",
      "value": 49,
      "delta": -1
    }
  },
  "value": 44,
  "fear_greed": 24,
  "news_sentiment": 49,
  "price_sentiment": 48,
  "price_change_24h": -0.61996,
  "liquidity_sentiment": 49
}