{
  "timestamp": "2026-01-12T19:24:41.070159",
  "total": {
    "value": 46
  },
  "drivers": {
    "fear_greed": {
      "label": "Fear & Greed",
      "value": 27,
      "delta": 0
    },
    "news": {
      "label": "News Sentiment",
      "value": 52,
      "delta": 5
    },
    "social": {
      "label": "Social Buzz",
      "value": 46,
      "delta": 3
    },
    "price_action": {
      "label": "Price Action",
      "value": 53,
      "delta": 1
    },
    "on_chain": {
      "label": "On-chain Activity",
      "value": 50,
      "delta": 6
    },
    "liquidity": {
      "label": "Liquidity",
      "value": 54,
      "delta": 1
    }
  },
  "value": 46,
  "fear_greed": 27,
  "news_sentiment": 52,
  "price_sentiment": 53,
  "price_change_24h": 1.0283,
  "liquidity_sentiment": 54
}