{
  "timestamp": "2026-02-09T18:29:24.317036",
  "total": {
    "value": 41
  },
  "drivers": {
    "fear_greed": {
      "label": "Fear & Greed",
      "value": 14,
      "delta": 0
    },
    "news": {
      "label": "News Sentiment",
      "value": 47,
      "delta": -1
    },
    "social": {
      "label": "Social Buzz",
      "value": 51,
      "delta": 14
    },
    "price_action": {
      "label": "Price Action",
      "value": 47,
      "delta": 0
    },
    "on_chain": {
      "label": "On-chain Activity",
      "value": 54,
      "delta": 1
    },
    "liquidity": {
      "label": "Liquidity",
      "value": 40,
      "delta": 1
    }
  },
  "value": 41,
  "fear_greed": 14,
  "news_sentiment": 47,
  "price_sentiment": 47,
  "price_change_24h": -1.01697,
  "liquidity_sentiment": 40
}