{
  "timestamp": "2026-01-28T19:34:01.154410",
  "total": {
    "value": 47
  },
  "drivers": {
    "fear_greed": {
      "label": "Fear & Greed",
      "value": 29,
      "delta": 0
    },
    "news": {
      "label": "News Sentiment",
      "value": 46,
      "delta": -5
    },
    "social": {
      "label": "Social Buzz",
      "value": 49,
      "delta": 6
    },
    "price_action": {
      "label": "Price Action",
      "value": 54,
      "delta": -2
    },
    "on_chain": {
      "label": "On-chain Activity",
      "value": 56,
      "delta": 3
    },
    "liquidity": {
      "label": "Liquidity",
      "value": 54,
      "delta": 1
    }
  },
  "value": 47,
  "fear_greed": 29,
  "news_sentiment": 46,
  "price_sentiment": 54,
  "price_change_24h": 1.27129,
  "liquidity_sentiment": 54
}