{
  "timestamp": "2026-01-08T04:43:25.799006",
  "total": {
    "value": 44
  },
  "drivers": {
    "fear_greed": {
      "label": "Fear & Greed",
      "value": 28,
      "delta": 0
    },
    "news": {
      "label": "News Sentiment",
      "value": 45,
      "delta": -5
    },
    "social": {
      "label": "Social Buzz",
      "value": 51,
      "delta": -6
    },
    "price_action": {
      "label": "Price Action",
      "value": 45,
      "delta": 2
    },
    "on_chain": {
      "label": "On-chain Activity",
      "value": 52,
      "delta": 6
    },
    "liquidity": {
      "label": "Liquidity",
      "value": 51,
      "delta": 0
    }
  },
  "value": 44,
  "fear_greed": 28,
  "news_sentiment": 45,
  "price_sentiment": 45,
  "price_change_24h": -1.78788,
  "liquidity_sentiment": 51
}