{
  "timestamp": "2026-02-07T20:34:10.714051",
  "total": {
    "value": 40
  },
  "drivers": {
    "fear_greed": {
      "label": "Fear & Greed",
      "value": 6,
      "delta": 0
    },
    "news": {
      "label": "News Sentiment",
      "value": 52,
      "delta": 0
    },
    "social": {
      "label": "Social Buzz",
      "value": 51,
      "delta": 0
    },
    "price_action": {
      "label": "Price Action",
      "value": 45,
      "delta": 0
    },
    "on_chain": {
      "label": "On-chain Activity",
      "value": 49,
      "delta": -6
    },
    "liquidity": {
      "label": "Liquidity",
      "value": 46,
      "delta": 0
    }
  },
  "value": 40,
  "fear_greed": 6,
  "news_sentiment": 52,
  "price_sentiment": 45,
  "price_change_24h": -1.62039,
  "liquidity_sentiment": 46
}